EntropyHub/_ApEn.py
EntropyHub/_AttnEn.py
EntropyHub/_BubbEn.py
EntropyHub/_CoSiEn.py
EntropyHub/_CondEn.py
EntropyHub/_DispEn.py
EntropyHub/_DispEn2D.py
EntropyHub/_DistEn.py
EntropyHub/_DistEn2D.py
EntropyHub/_DivEn.py
EntropyHub/_EnofEn.py
EntropyHub/_EspEn2D.py
EntropyHub/_ExampleData.py
EntropyHub/_FuzzEn.py
EntropyHub/_FuzzEn2D.py
EntropyHub/_GridEn.py
EntropyHub/_IncrEn.py
EntropyHub/_K2En.py
EntropyHub/_MSEn.py
EntropyHub/_MSEn2D.py
EntropyHub/_MSobject.py
EntropyHub/_MvCoSiEn.py
EntropyHub/_MvDispEn.py
EntropyHub/_MvFuzzEn.py
EntropyHub/_MvMSEn.py
EntropyHub/_MvPermEn.py
EntropyHub/_MvSampEn.py
EntropyHub/_PermEn.py
EntropyHub/_PermEn2D.py
EntropyHub/_PhasEn.py
EntropyHub/_RangEn.py
EntropyHub/_SampEn.py
EntropyHub/_SampEn2D.py
EntropyHub/_SlopEn.py
EntropyHub/_SpecEn.py
EntropyHub/_SyDyEn.py
EntropyHub/_WindowData.py
EntropyHub/_XApEn.py
EntropyHub/_XCondEn.py
EntropyHub/_XDistEn.py
EntropyHub/_XFuzzEn.py
EntropyHub/_XK2En.py
EntropyHub/_XMSEn.py
EntropyHub/_XPermEn.py
EntropyHub/_XSampEn.py
EntropyHub/_XSpecEn.py
EntropyHub/__init__.py
EntropyHub/_cMSEn.py
EntropyHub/_cMvMSEn.py
EntropyHub/_cXMSEn.py
EntropyHub/_hMSEn.py
EntropyHub/_hXMSEn.py
EntropyHub/_rMSEn.py
EntropyHub/_rXMSEn.py
EntropyHub-2.0.dist-info/LICENSE.txt
EntropyHub-2.0.dist-info/METADATA
EntropyHub-2.0.dist-info/WHEEL
EntropyHub-2.0.dist-info/top_level.txt
EntropyHub-2.0.dist-info/RECORD
