Metadata-Version: 2.1
Name: EntropyHub
Version: 2.0
Summary: An open-source toolkit for entropic data analysis.
Author-email: "Matthew W. Flood" <info@entropyhub.xyz>
Maintainer-email: "Matthew W. Flood" <info@entropyhub.xyz>
License: Apache License
Project-URL: Homepage, https://www.EntropyHub.xyz/
Project-URL: Documentation, https://www.entropyhub.xyz/
Project-URL: Repository, https://github.com/MattWillFlood/EntropyHub
Project-URL: User Manual, https://github.com/MattWillFlood/EntropyHub/blob/main/EntropyHub%20Guide.pdf
Project-URL: Citation, https://doi.org/10.1371/journal.pone.0259448
Project-URL: Bug Tracker, https://github.com/MattWillFlood/EntropyHub/issues
Project-URL: Contact, https://www.entropyhub.xyz/#contact
Project-URL: Examples, https://www.entropyhub.xyz/python/pyexamples.html
Keywords: entropy,nonlinear,time series,statistics,physics,mathematics,signal processing,statistical physics,entropic,toolkit,research,multiscale,regularity,periodic,sample entropy,approximate entropy,fuzzy entropy,permutation entropy,uncertainty,dispersion entropy,kolmogorov,conditional entropy,composite,refined,multivariate,randomness,random,signal analysis,nonlinearity,julia,matlab,open-source,refined-composite,hierarchical entropy,information theory,shannon entropy,complexity,dynamical,syste
Classifier: Development Status :: 5 - Production/Stable
Classifier: Intended Audience :: Science/Research
Classifier: Topic :: Scientific/Engineering
Classifier: License :: OSI Approved :: Apache Software License
Classifier: Natural Language :: English
Classifier: Operating System :: OS Independent
Classifier: Programming Language :: Python :: 3
Classifier: Programming Language :: Python :: 3.6
Classifier: Programming Language :: Python :: 3.7
Classifier: Programming Language :: Python :: 3.8
Classifier: Programming Language :: Python :: 3.9
Classifier: Programming Language :: Python :: 3 :: Only
Requires-Python: >=3.6
License-File: LICENSE.txt
Requires-Dist: numpy
Requires-Dist: matplotlib
Requires-Dist: scipy
Requires-Dist: EMD-signal
Requires-Dist: requests
